giga_json/__init__.py
giga_json/__version__.py
test/__init__.py
test/test_giga.py
giga_json-1.0.5.dist-info/LICENSE
giga_json-1.0.5.dist-info/METADATA
giga_json-1.0.5.dist-info/WHEEL
giga_json-1.0.5.dist-info/top_level.txt
giga_json-1.0.5.dist-info/RECORD
